MANIFEST.in
README.rst
requirements.txt
setup.py
sqsworkers/__init__.py
sqsworkers/bounded_executor.py
sqsworkers/crew.py
sqsworkers/interfaces.py
sqsworkers/listeners.py
sqsworkers.egg-info/PKG-INFO
sqsworkers.egg-info/SOURCES.txt
sqsworkers.egg-info/dependency_links.txt
sqsworkers.egg-info/requires.txt
sqsworkers.egg-info/top_level.txt