Metadata-Version: 2.1
Name: sqsworkers
Version: 1.0
Summary: UNKNOWN
Home-page: https://github.com/goodmanship/sqsworkers
Author: Rio Goodman
Author-email: riogoodman@gmail.com
License: Apache License 2.0
Platform: UNKNOWN
Provides-Extra: test
Provides-Extra: dev
